sphinx_code_examples/__init__.py
sphinx_code_examples/_compat.py
sphinx_code_examples/_version.py
sphinx_code_examples/directive.py
sphinx_code_examples/latex.py
sphinx_code_examples/nodes.py
sphinx_code_examples/post_transforms.py
sphinx_code_examples/transforms.py
sphinx_code_examples/utils.py
sphinx_code_examples/assets/html/codex.css
sphinx_code_examples/assets/html/dual_button.css
sphinx_code_examples/assets/html/dual_button.js
sphinx_code_examples/translations/README.md
sphinx_code_examples/translations/_convert.py
sphinx_code_examples/translations/jsons/Code example.json
sphinx_code_examples/translations/jsons/Example.json
sphinx_code_examples/translations/jsons/Textual.json
sphinx_code_examples/translations/jsons/Textual_text.json
sphinx_code_examples/translations/jsons/Visual.json
sphinx_code_examples/translations/jsons/Visual_text.json
sphinx_code_examples/translations/locales/ar/LC_MESSAGES/codex.mo
sphinx_code_examples/translations/locales/ar/LC_MESSAGES/codex.po
sphinx_code_examples/translations/locales/bn/LC_MESSAGES/codex.mo
sphinx_code_examples/translations/locales/bn/LC_MESSAGES/codex.po
sphinx_code_examples/translations/locales/cs/LC_MESSAGES/codex.mo
sphinx_code_examples/translations/locales/cs/LC_MESSAGES/codex.po
sphinx_code_examples/translations/locales/de/LC_MESSAGES/codex.mo
sphinx_code_examples/translations/locales/de/LC_MESSAGES/codex.po
sphinx_code_examples/translations/locales/el/LC_MESSAGES/codex.mo
sphinx_code_examples/translations/locales/el/LC_MESSAGES/codex.po
sphinx_code_examples/translations/locales/es/LC_MESSAGES/codex.mo
sphinx_code_examples/translations/locales/es/LC_MESSAGES/codex.po
sphinx_code_examples/translations/locales/fa/LC_MESSAGES/codex.mo
sphinx_code_examples/translations/locales/fa/LC_MESSAGES/codex.po
sphinx_code_examples/translations/locales/fr/LC_MESSAGES/codex.mo
sphinx_code_examples/translations/locales/fr/LC_MESSAGES/codex.po
sphinx_code_examples/translations/locales/he/LC_MESSAGES/codex.mo
sphinx_code_examples-1.2.3.dist-info/METADATA
sphinx_code_examples-1.2.3.dist-info/WHEEL
sphinx_code_examples-1.2.3.dist-info/licenses/LICENSE
sphinx_code_examples-1.2.3.dist-info/RECORD
