Metadata-Version: 2.4
Name: sphinx-code-examples
Version: 1.2.3
Summary: A Sphinx extension that provides an interface to examples with runnable code.
Author-email: Dennis den Ouden-van der Horst <d.denouden-vanderhorst@tudelft.nl>
License: MIT License
License-File: LICENSE
Requires-Python: >=3.10
Requires-Dist: sphinx
Requires-Dist: sphinx-iframes>=1.0.7
Requires-Dist: sphinx-proof
